{
  "project_info": {
    "project_number": "305311030746",
    "firebase_url": "https://scanner-document-35f47.firebaseio.com",
    "project_id": "scanner-document-35f47",
    "storage_bucket": "scanner-document-35f47.appspot.com"
  },
  "client": [
    {
      "client_info": {
        "mobilesdk_app_id": "1:305311030746:android:fcc8169ce2b331354134e3",
        "android_client_info": {
          "package_name": "com.example.myabc"
        }
      },
      "oauth_client": [
        {
          "client_id": "305311030746-d1r0bitgbs5o0gmirdnv4o1mt43ngrrv.apps.googleusercontent.com",
          "client_type": 3
        }
      ],
      "api_key": [
        {
          "current_key": "AIzaSyA8uSSDLIk9TxqZ03G65mV2CC8cqk_VEs0"
        }
      ],
      "services": {
        "appinvite_service": {
          "other_platform_oauth_client": [
            {
              "client_id": "305311030746-d1r0bitgbs5o0gmirdnv4o1mt43ngrrv.apps.googleusercontent.com",
              "client_type": 3
            }
          ]
        }
      }
    }
  ],
  "configuration_version": "1"
}